{
    "interatomicPotentialImplementationLAMMPS": {
        "potentialID": {
            "descriptionIdentifier": "Fe--ProvilleL--2012"
        },
        "units": "metal",
        "atom_style": "atomic",
        "atom": {
            "element": "Fe",
            "mass": 55.845
        },
        "pair_style": {
            "type": "eam/alloy"
        },
        "pair_coeff": {
            "term": [
                {
                    "file": "Fe_Proville.eam.alloy"
                },
                {
                    "symbols": "True"
                }
            ]
        }
    }
}